cdk_codebuild_sonarcloud/__init__.py
cdk_codebuild_sonarcloud/py.typed
cdk_codebuild_sonarcloud/_jsii/__init__.py
cdk_codebuild_sonarcloud/_jsii/cdk-codebuild-sonarcloud@0.0.2.jsii.tgz
cdk_codebuild_sonarcloud-0.0.2.dist-info/LICENSE
cdk_codebuild_sonarcloud-0.0.2.dist-info/METADATA
cdk_codebuild_sonarcloud-0.0.2.dist-info/WHEEL
cdk_codebuild_sonarcloud-0.0.2.dist-info/top_level.txt
cdk_codebuild_sonarcloud-0.0.2.dist-info/RECORD
